finsights/__init__.py
finsights/analysis.py
finsights/data.py
finsights-1.0.0.dist-info/LICENSE
finsights-1.0.0.dist-info/METADATA
finsights-1.0.0.dist-info/WHEEL
finsights-1.0.0.dist-info/top_level.txt
finsights-1.0.0.dist-info/RECORD
