Metadata-Version: 2.1
Name: finsights
Version: 1.0.0
Summary: Derive investment insights
Home-page: https://gitlab.com/qiujunda/finsights
Author: Finsights
License: MIT
Platform: UNKNOWN
Classifier: License :: OSI Approved :: MIT License
Classifier: Programming Language :: Python :: 3.6
Classifier: Programming Language :: Python :: 3.7
Classifier: Programming Language :: Python :: 3.8
Classifier: Operating System :: MacOS
Requires-Python: >=3.6
